vertez.cp310-win_amd64.pyd
vertez-1.0.0.dist-info/METADATA
vertez-1.0.0.dist-info/WHEEL
vertez-1.0.0.dist-info/top_level.txt
vertez-1.0.0.dist-info/RECORD
