Metadata-Version: 2.1
Name: vertez
Version: 1.0.0
Summary: Vertez: Statify and Infer
Author: Ravinthiran Partheepan
License: UNKNOWN
Platform: UNKNOWN
Requires-Dist: pybind11
